[
    [
        {
            "Step": 1,
            "Gini": 0.3782066842316636
        },
        {
            "Step": 2,
            "Gini": 0.36633121247972134
        },
        {
            "Step": 3,
            "Gini": 0.3044863558735751
        },
        {
            "Step": 4,
            "Gini": 0.30954989083471385
        },
        {
            "Step": 5,
            "Gini": 0.3461862914329785
        },
        {
            "Step": 6,
            "Gini": 0.3195758212003845
        },
        {
            "Step": 7,
            "Gini": 0.3108503007188299
        },
        {
            "Step": 8,
            "Gini": 0.2824266739411747
        },
        {
            "Step": 9,
            "Gini": 0.27006448575517106
        },
        {
            "Step": 10,
            "Gini": 0.25921235323276215
        },
        {
            "Step": 11,
            "Gini": 0.2575274061671178
        },
        {
            "Step": 12,
            "Gini": 0.23535742310375762
        },
        {
            "Step": 13,
            "Gini": 0.23155359962094058
        },
        {
            "Step": 14,
            "Gini": 0.22511435397649704
        },
        {
            "Step": 15,
            "Gini": 0.22003345374840433
        },
        {
            "Step": 16,
            "Gini": 0.21213693118147714
        },
        {
            "Step": 17,
            "Gini": 0.21217681605722438
        },
        {
            "Step": 18,
            "Gini": 0.21580472211738333
        },
        {
            "Step": 19,
            "Gini": 0.21871105738227525
        },
        {
            "Step": 20,
            "Gini": 0.21304794270284688
        },
        {
            "Step": 21,
            "Gini": 0.21520435509196778
        },
        {
            "Step": 22,
            "Gini": 0.2160349491236575
        },
        {
            "Step": 23,
            "Gini": 0.20821695612167046
        },
        {
            "Step": 24,
            "Gini": 0.20688571355786012
        },
        {
            "Step": 25,
            "Gini": 0.21035020204408306
        },
        {
            "Step": 26,
            "Gini": 0.21255664455463408
        },
        {
            "Step": 27,
            "Gini": 0.21334938109917623
        },
        {
            "Step": 28,
            "Gini": 0.21503362616344113
        },
        {
            "Step": 29,
            "Gini": 0.21349103109394574
        },
        {
            "Step": 30,
            "Gini": 0.21757143167773485
        },
        {
            "Step": 31,
            "Gini": 0.21563034650786506
        },
        {
            "Step": 32,
            "Gini": 0.21989353667009826
        },
        {
            "Step": 33,
            "Gini": 0.21607824438671996
        },
        {
            "Step": 34,
            "Gini": 0.21293341815982392
        },
        {
            "Step": 35,
            "Gini": 0.21522760275310548
        },
        {
            "Step": 36,
            "Gini": 0.22105172558736563
        },
        {
            "Step": 37,
            "Gini": 0.2196916613685782
        },
        {
            "Step": 38,
            "Gini": 0.22144014667983392
        },
        {
            "Step": 39,
            "Gini": 0.22510562981018123
        },
        {
            "Step": 40,
            "Gini": 0.2341672282048588
        },
        {
            "Step": 41,
            "Gini": 0.23374569623128472
        },
        {
            "Step": 42,
            "Gini": 0.2360596445205314
        },
        {
            "Step": 43,
            "Gini": 0.24203606580442139
        },
        {
            "Step": 44,
            "Gini": 0.24193778550496825
        },
        {
            "Step": 45,
            "Gini": 0.24219350901920644
        },
        {
            "Step": 46,
            "Gini": 0.2466760207542824
        },
        {
            "Step": 47,
            "Gini": 0.2416851243965188
        },
        {
            "Step": 48,
            "Gini": 0.24773186438154826
        },
        {
            "Step": 49,
            "Gini": 0.24938447710478084
        },
        {
            "Step": 50,
            "Gini": 0.2521072530053372
        },
        {
            "Step": 51,
            "Gini": 0.2577015205769988
        },
        {
            "Step": 52,
            "Gini": 0.2627625418195054
        },
        {
            "Step": 53,
            "Gini": 0.26560914393656265
        },
        {
            "Step": 54,
            "Gini": 0.26211792293198366
        },
        {
            "Step": 55,
            "Gini": 0.2657719723940577
        },
        {
            "Step": 56,
            "Gini": 0.2672623171219193
        },
        {
            "Step": 57,
            "Gini": 0.2731568510147524
        },
        {
            "Step": 58,
            "Gini": 0.2704299336587235
        },
        {
            "Step": 59,
            "Gini": 0.2741204227925389
        },
        {
            "Step": 60,
            "Gini": 0.2764431923880193
        },
        {
            "Step": 61,
            "Gini": 0.2819938661169439
        },
        {
            "Step": 62,
            "Gini": 0.2815597405966228
        },
        {
            "Step": 63,
            "Gini": 0.2861194760460064
        },
        {
            "Step": 64,
            "Gini": 0.28430418398275226
        },
        {
            "Step": 65,
            "Gini": 0.29166537552883565
        },
        {
            "Step": 66,
            "Gini": 0.2988459033257831
        },
        {
            "Step": 67,
            "Gini": 0.3035155112871162
        },
        {
            "Step": 68,
            "Gini": 0.3075818282456526
        },
        {
            "Step": 69,
            "Gini": 0.3093445662519556
        },
        {
            "Step": 70,
            "Gini": 0.3146270831288147
        },
        {
            "Step": 71,
            "Gini": 0.3162954595451153
        },
        {
            "Step": 72,
            "Gini": 0.3191477189838876
        },
        {
            "Step": 73,
            "Gini": 0.3262114159028211
        },
        {
            "Step": 74,
            "Gini": 0.3329551884318134
        },
        {
            "Step": 75,
            "Gini": 0.33517888431717924
        },
        {
            "Step": 76,
            "Gini": 0.3360809643108713
        },
        {
            "Step": 77,
            "Gini": 0.3371197118903486
        },
        {
            "Step": 78,
            "Gini": 0.33930169800614607
        },
        {
            "Step": 79,
            "Gini": 0.3372234836856043
        },
        {
            "Step": 80,
            "Gini": 0.34322666810445424
        }
    ],
    [
        {
            "Step": 1,
            "Gini": 0.5532528748478054
        },
        {
            "Step": 2,
            "Gini": 0.540233170913925
        },
        {
            "Step": 3,
            "Gini": 0.4132402898045664
        },
        {
            "Step": 4,
            "Gini": 0.34106924929938365
        },
        {
            "Step": 5,
            "Gini": 0.301886863943692
        },
        {
            "Step": 6,
            "Gini": 0.268807797840906
        },
        {
            "Step": 7,
            "Gini": 0.2494897247898089
        },
        {
            "Step": 8,
            "Gini": 0.23154451181726476
        },
        {
            "Step": 9,
            "Gini": 0.22121333641340812
        },
        {
            "Step": 10,
            "Gini": 0.2154165578741678
        },
        {
            "Step": 11,
            "Gini": 0.20578640538801984
        },
        {
            "Step": 12,
            "Gini": 0.20023368689210974
        },
        {
            "Step": 13,
            "Gini": 0.1992479037302295
        },
        {
            "Step": 14,
            "Gini": 0.2057878524751633
        },
        {
            "Step": 15,
            "Gini": 0.20686874739402983
        },
        {
            "Step": 16,
            "Gini": 0.2019438642050777
        },
        {
            "Step": 17,
            "Gini": 0.19408530214784636
        },
        {
            "Step": 18,
            "Gini": 0.18693597328718825
        },
        {
            "Step": 19,
            "Gini": 0.18164937582134688
        },
        {
            "Step": 20,
            "Gini": 0.18533557754586694
        },
        {
            "Step": 21,
            "Gini": 0.1881013491249932
        },
        {
            "Step": 22,
            "Gini": 0.19289591155060948
        },
        {
            "Step": 23,
            "Gini": 0.1894358915544223
        },
        {
            "Step": 24,
            "Gini": 0.18657801816088848
        },
        {
            "Step": 25,
            "Gini": 0.1892168712592044
        },
        {
            "Step": 26,
            "Gini": 0.18534366121409684
        },
        {
            "Step": 27,
            "Gini": 0.18779746460124658
        },
        {
            "Step": 28,
            "Gini": 0.19412130235408465
        },
        {
            "Step": 29,
            "Gini": 0.1962377773027817
        },
        {
            "Step": 30,
            "Gini": 0.19776428600796825
        },
        {
            "Step": 31,
            "Gini": 0.1942352467433177
        },
        {
            "Step": 32,
            "Gini": 0.1979515034919399
        },
        {
            "Step": 33,
            "Gini": 0.19911779949727393
        },
        {
            "Step": 34,
            "Gini": 0.1919100709361019
        },
        {
            "Step": 35,
            "Gini": 0.19616648484044585
        },
        {
            "Step": 36,
            "Gini": 0.19634876321992678
        },
        {
            "Step": 37,
            "Gini": 0.19711846061142713
        },
        {
            "Step": 38,
            "Gini": 0.19421188446548276
        },
        {
            "Step": 39,
            "Gini": 0.19978323754329952
        },
        {
            "Step": 40,
            "Gini": 0.2017905090842913
        },
        {
            "Step": 41,
            "Gini": 0.19867302459806369
        },
        {
            "Step": 42,
            "Gini": 0.19922450172175354
        },
        {
            "Step": 43,
            "Gini": 0.20117098419856805
        },
        {
            "Step": 44,
            "Gini": 0.20345935596824583
        },
        {
            "Step": 45,
            "Gini": 0.206146882439177
        },
        {
            "Step": 46,
            "Gini": 0.2099906924894237
        },
        {
            "Step": 47,
            "Gini": 0.20611430091229566
        },
        {
            "Step": 48,
            "Gini": 0.21153643597817573
        },
        {
            "Step": 49,
            "Gini": 0.21879054394459319
        },
        {
            "Step": 50,
            "Gini": 0.2209092727510027
        },
        {
            "Step": 51,
            "Gini": 0.21521792566000486
        },
        {
            "Step": 52,
            "Gini": 0.21682044691182112
        },
        {
            "Step": 53,
            "Gini": 0.2159642879424717
        },
        {
            "Step": 54,
            "Gini": 0.22383141101918613
        },
        {
            "Step": 55,
            "Gini": 0.22380307019904766
        },
        {
            "Step": 56,
            "Gini": 0.22684272603269062
        },
        {
            "Step": 57,
            "Gini": 0.22734759167625973
        },
        {
            "Step": 58,
            "Gini": 0.23197589098520788
        },
        {
            "Step": 59,
            "Gini": 0.2340071736544782
        },
        {
            "Step": 60,
            "Gini": 0.23536828068725835
        },
        {
            "Step": 61,
            "Gini": 0.2378817125979833
        },
        {
            "Step": 62,
            "Gini": 0.24002556525377594
        },
        {
            "Step": 63,
            "Gini": 0.24249104863613047
        },
        {
            "Step": 64,
            "Gini": 0.23734637041801387
        },
        {
            "Step": 65,
            "Gini": 0.23592590542598701
        },
        {
            "Step": 66,
            "Gini": 0.23934936878928204
        },
        {
            "Step": 67,
            "Gini": 0.24125958203990683
        },
        {
            "Step": 68,
            "Gini": 0.2518316768557094
        },
        {
            "Step": 69,
            "Gini": 0.25891731366973114
        },
        {
            "Step": 70,
            "Gini": 0.2591822637197079
        },
        {
            "Step": 71,
            "Gini": 0.2558528312140951
        },
        {
            "Step": 72,
            "Gini": 0.2571855476100475
        },
        {
            "Step": 73,
            "Gini": 0.2580961513485105
        },
        {
            "Step": 74,
            "Gini": 0.2620201925416472
        },
        {
            "Step": 75,
            "Gini": 0.2657829566451513
        },
        {
            "Step": 76,
            "Gini": 0.2668425709362441
        },
        {
            "Step": 77,
            "Gini": 0.2650134934418067
        },
        {
            "Step": 78,
            "Gini": 0.2677692155682436
        },
        {
            "Step": 79,
            "Gini": 0.26943018530206375
        },
        {
            "Step": 80,
            "Gini": 0.26891349044270707
        }
    ],
    [
        {
            "Step": 1,
            "Gini": 0.38903113783895016
        },
        {
            "Step": 2,
            "Gini": 0.30635715437751077
        },
        {
            "Step": 3,
            "Gini": 0.4298166091055635
        },
        {
            "Step": 4,
            "Gini": 0.3664277833272609
        },
        {
            "Step": 5,
            "Gini": 0.3374244754691871
        },
        {
            "Step": 6,
            "Gini": 0.32145600309689404
        },
        {
            "Step": 7,
            "Gini": 0.30917049949081266
        },
        {
            "Step": 8,
            "Gini": 0.2761370213939571
        },
        {
            "Step": 9,
            "Gini": 0.26019186690231355
        },
        {
            "Step": 10,
            "Gini": 0.2479715742166846
        },
        {
            "Step": 11,
            "Gini": 0.24417537872412565
        },
        {
            "Step": 12,
            "Gini": 0.25186060645201813
        },
        {
            "Step": 13,
            "Gini": 0.23853984621467061
        },
        {
            "Step": 14,
            "Gini": 0.22826137958171988
        },
        {
            "Step": 15,
            "Gini": 0.2184965358602986
        },
        {
            "Step": 16,
            "Gini": 0.21172411263779045
        },
        {
            "Step": 17,
            "Gini": 0.21050400630956712
        },
        {
            "Step": 18,
            "Gini": 0.21656909573081617
        },
        {
            "Step": 19,
            "Gini": 0.21217208568931833
        },
        {
            "Step": 20,
            "Gini": 0.20336538172364782
        },
        {
            "Step": 21,
            "Gini": 0.20198676985585173
        },
        {
            "Step": 22,
            "Gini": 0.20312470214559353
        },
        {
            "Step": 23,
            "Gini": 0.20284335564043632
        },
        {
            "Step": 24,
            "Gini": 0.206815894764677
        },
        {
            "Step": 25,
            "Gini": 0.20478342756992474
        },
        {
            "Step": 26,
            "Gini": 0.20236438595084638
        },
        {
            "Step": 27,
            "Gini": 0.20162991084985693
        },
        {
            "Step": 28,
            "Gini": 0.20958158858554032
        },
        {
            "Step": 29,
            "Gini": 0.20470901214707138
        },
        {
            "Step": 30,
            "Gini": 0.19924234121683382
        },
        {
            "Step": 31,
            "Gini": 0.19554339434705326
        },
        {
            "Step": 32,
            "Gini": 0.1910244866540649
        },
        {
            "Step": 33,
            "Gini": 0.1930782603690704
        },
        {
            "Step": 34,
            "Gini": 0.1903617742922552
        },
        {
            "Step": 35,
            "Gini": 0.193949044850378
        },
        {
            "Step": 36,
            "Gini": 0.19504449319345585
        },
        {
            "Step": 37,
            "Gini": 0.1937161097944755
        },
        {
            "Step": 38,
            "Gini": 0.19304127990538422
        },
        {
            "Step": 39,
            "Gini": 0.19721178376478044
        },
        {
            "Step": 40,
            "Gini": 0.1973562070668211
        },
        {
            "Step": 41,
            "Gini": 0.1933146711345204
        },
        {
            "Step": 42,
            "Gini": 0.19399242733440647
        },
        {
            "Step": 43,
            "Gini": 0.19510947070794793
        },
        {
            "Step": 44,
            "Gini": 0.19954913148391573
        },
        {
            "Step": 45,
            "Gini": 0.20268411168342837
        },
        {
            "Step": 46,
            "Gini": 0.20013584861385736
        },
        {
            "Step": 47,
            "Gini": 0.20506741236186787
        },
        {
            "Step": 48,
            "Gini": 0.20536595827482929
        },
        {
            "Step": 49,
            "Gini": 0.21173416767004705
        },
        {
            "Step": 50,
            "Gini": 0.21105473498461946
        },
        {
            "Step": 51,
            "Gini": 0.21314176365188175
        },
        {
            "Step": 52,
            "Gini": 0.21322792527529022
        },
        {
            "Step": 53,
            "Gini": 0.21976636216206313
        },
        {
            "Step": 54,
            "Gini": 0.22306797194339523
        },
        {
            "Step": 55,
            "Gini": 0.22443618820965328
        },
        {
            "Step": 56,
            "Gini": 0.22614821900107596
        },
        {
            "Step": 57,
            "Gini": 0.2287363184786546
        },
        {
            "Step": 58,
            "Gini": 0.22488716774758877
        },
        {
            "Step": 59,
            "Gini": 0.2259286254467785
        },
        {
            "Step": 60,
            "Gini": 0.22218553011300535
        },
        {
            "Step": 61,
            "Gini": 0.22696840037139698
        },
        {
            "Step": 62,
            "Gini": 0.22446049458358175
        },
        {
            "Step": 63,
            "Gini": 0.22682591455906032
        },
        {
            "Step": 64,
            "Gini": 0.2245821801426724
        },
        {
            "Step": 65,
            "Gini": 0.22975885340033186
        },
        {
            "Step": 66,
            "Gini": 0.23178383145889714
        },
        {
            "Step": 67,
            "Gini": 0.22888691070056866
        },
        {
            "Step": 68,
            "Gini": 0.2281446032597949
        },
        {
            "Step": 69,
            "Gini": 0.22999922914386772
        },
        {
            "Step": 70,
            "Gini": 0.2363213922643188
        },
        {
            "Step": 71,
            "Gini": 0.2395441574679178
        },
        {
            "Step": 72,
            "Gini": 0.244352194274299
        },
        {
            "Step": 73,
            "Gini": 0.24690468001437926
        },
        {
            "Step": 74,
            "Gini": 0.2476437336055024
        },
        {
            "Step": 75,
            "Gini": 0.2471859995946497
        },
        {
            "Step": 76,
            "Gini": 0.24462072493528186
        },
        {
            "Step": 77,
            "Gini": 0.24348588423696627
        },
        {
            "Step": 78,
            "Gini": 0.23794674288196305
        },
        {
            "Step": 79,
            "Gini": 0.24143040511035396
        },
        {
            "Step": 80,
            "Gini": 0.23759638077238665
        }
    ],
    [
        {
            "Step": 1,
            "Gini": 0.6210722308584078
        },
        {
            "Step": 2,
            "Gini": 0.5280823351172712
        },
        {
            "Step": 3,
            "Gini": 0.46693242573422955
        },
        {
            "Step": 4,
            "Gini": 0.4046433971139496
        },
        {
            "Step": 5,
            "Gini": 0.3200729687286199
        },
        {
            "Step": 6,
            "Gini": 0.28904643087586246
        },
        {
            "Step": 7,
            "Gini": 0.2686630275476267
        },
        {
            "Step": 8,
            "Gini": 0.24524450100627404
        },
        {
            "Step": 9,
            "Gini": 0.2494301968125887
        },
        {
            "Step": 10,
            "Gini": 0.23671647526114836
        },
        {
            "Step": 11,
            "Gini": 0.22132157677835118
        },
        {
            "Step": 12,
            "Gini": 0.21108691720004868
        },
        {
            "Step": 13,
            "Gini": 0.21027833032081045
        },
        {
            "Step": 14,
            "Gini": 0.1997416388209894
        },
        {
            "Step": 15,
            "Gini": 0.2025318113975112
        },
        {
            "Step": 16,
            "Gini": 0.1951589928620967
        },
        {
            "Step": 17,
            "Gini": 0.18905898270473842
        },
        {
            "Step": 18,
            "Gini": 0.17697126972708843
        },
        {
            "Step": 19,
            "Gini": 0.17579456184883702
        },
        {
            "Step": 20,
            "Gini": 0.17557328401105354
        },
        {
            "Step": 21,
            "Gini": 0.16937163624297624
        },
        {
            "Step": 22,
            "Gini": 0.17014008222639232
        },
        {
            "Step": 23,
            "Gini": 0.17117223681430915
        },
        {
            "Step": 24,
            "Gini": 0.16858981972481635
        },
        {
            "Step": 25,
            "Gini": 0.16728526420685141
        },
        {
            "Step": 26,
            "Gini": 0.16744410944813892
        },
        {
            "Step": 27,
            "Gini": 0.16611125548085126
        },
        {
            "Step": 28,
            "Gini": 0.1661527264623397
        },
        {
            "Step": 29,
            "Gini": 0.16464573299901053
        },
        {
            "Step": 30,
            "Gini": 0.16144878956653708
        },
        {
            "Step": 31,
            "Gini": 0.16889169203193832
        },
        {
            "Step": 32,
            "Gini": 0.17451078906695794
        },
        {
            "Step": 33,
            "Gini": 0.17759131631131808
        },
        {
            "Step": 34,
            "Gini": 0.18166911267986197
        },
        {
            "Step": 35,
            "Gini": 0.1756162103766179
        },
        {
            "Step": 36,
            "Gini": 0.17883879665286972
        },
        {
            "Step": 37,
            "Gini": 0.17981953820235597
        },
        {
            "Step": 38,
            "Gini": 0.18519067831964486
        },
        {
            "Step": 39,
            "Gini": 0.18286149818695674
        },
        {
            "Step": 40,
            "Gini": 0.17925763016787455
        },
        {
            "Step": 41,
            "Gini": 0.1797026870469467
        },
        {
            "Step": 42,
            "Gini": 0.17828512304578847
        },
        {
            "Step": 43,
            "Gini": 0.18167736543864077
        },
        {
            "Step": 44,
            "Gini": 0.18722367930314232
        },
        {
            "Step": 45,
            "Gini": 0.18583302667601664
        },
        {
            "Step": 46,
            "Gini": 0.1866760453153129
        },
        {
            "Step": 47,
            "Gini": 0.19345653006874208
        },
        {
            "Step": 48,
            "Gini": 0.19855326216422764
        },
        {
            "Step": 49,
            "Gini": 0.19948302810457474
        },
        {
            "Step": 50,
            "Gini": 0.19970007348455687
        },
        {
            "Step": 51,
            "Gini": 0.2025629796293995
        },
        {
            "Step": 52,
            "Gini": 0.20523327301317273
        },
        {
            "Step": 53,
            "Gini": 0.2116464273162646
        },
        {
            "Step": 54,
            "Gini": 0.21483130303174436
        },
        {
            "Step": 55,
            "Gini": 0.2188589823026239
        },
        {
            "Step": 56,
            "Gini": 0.22211733968367775
        },
        {
            "Step": 57,
            "Gini": 0.22415538130398938
        },
        {
            "Step": 58,
            "Gini": 0.22165865591777423
        },
        {
            "Step": 59,
            "Gini": 0.22742436317691683
        },
        {
            "Step": 60,
            "Gini": 0.2266875188855706
        },
        {
            "Step": 61,
            "Gini": 0.22900830347740686
        },
        {
            "Step": 62,
            "Gini": 0.23413495235561754
        },
        {
            "Step": 63,
            "Gini": 0.23216456473691727
        },
        {
            "Step": 64,
            "Gini": 0.23486482574027923
        },
        {
            "Step": 65,
            "Gini": 0.23935152818209082
        },
        {
            "Step": 66,
            "Gini": 0.2436988855086457
        },
        {
            "Step": 67,
            "Gini": 0.24603547289856142
        },
        {
            "Step": 68,
            "Gini": 0.24897744950901046
        },
        {
            "Step": 69,
            "Gini": 0.25648642167806024
        },
        {
            "Step": 70,
            "Gini": 0.25702133623843193
        },
        {
            "Step": 71,
            "Gini": 0.2520361362095407
        },
        {
            "Step": 72,
            "Gini": 0.2556474555207977
        },
        {
            "Step": 73,
            "Gini": 0.2609840354281001
        },
        {
            "Step": 74,
            "Gini": 0.2609563221143625
        },
        {
            "Step": 75,
            "Gini": 0.26162419949756854
        },
        {
            "Step": 76,
            "Gini": 0.2660696790725794
        },
        {
            "Step": 77,
            "Gini": 0.26624927067863635
        },
        {
            "Step": 78,
            "Gini": 0.27311706664266033
        },
        {
            "Step": 79,
            "Gini": 0.27516505055376017
        },
        {
            "Step": 80,
            "Gini": 0.273900280224354
        }
    ],
    [
        {
            "Step": 1,
            "Gini": 0.6617757729826859
        },
        {
            "Step": 2,
            "Gini": 0.46048094379458804
        },
        {
            "Step": 3,
            "Gini": 0.35886989851125306
        },
        {
            "Step": 4,
            "Gini": 0.3141060359156398
        },
        {
            "Step": 5,
            "Gini": 0.30553699386846556
        },
        {
            "Step": 6,
            "Gini": 0.31076838675298424
        },
        {
            "Step": 7,
            "Gini": 0.29187239523016273
        },
        {
            "Step": 8,
            "Gini": 0.26488210794736267
        },
        {
            "Step": 9,
            "Gini": 0.25168153777647895
        },
        {
            "Step": 10,
            "Gini": 0.24758608758329825
        },
        {
            "Step": 11,
            "Gini": 0.235054340878865
        },
        {
            "Step": 12,
            "Gini": 0.22085004391394714
        },
        {
            "Step": 13,
            "Gini": 0.21739888920483952
        },
        {
            "Step": 14,
            "Gini": 0.21449258779005054
        },
        {
            "Step": 15,
            "Gini": 0.21281619849098
        },
        {
            "Step": 16,
            "Gini": 0.20999231513882521
        },
        {
            "Step": 17,
            "Gini": 0.212199530283544
        },
        {
            "Step": 18,
            "Gini": 0.21847680190343954
        },
        {
            "Step": 19,
            "Gini": 0.2161059881534375
        },
        {
            "Step": 20,
            "Gini": 0.21829221612263838
        },
        {
            "Step": 21,
            "Gini": 0.21477081892733207
        },
        {
            "Step": 22,
            "Gini": 0.2104659138174283
        },
        {
            "Step": 23,
            "Gini": 0.206718279019785
        },
        {
            "Step": 24,
            "Gini": 0.2095180001951369
        },
        {
            "Step": 25,
            "Gini": 0.20989238521762021
        },
        {
            "Step": 26,
            "Gini": 0.21341505881533163
        },
        {
            "Step": 27,
            "Gini": 0.2142985328268665
        },
        {
            "Step": 28,
            "Gini": 0.21723468705008653
        },
        {
            "Step": 29,
            "Gini": 0.2209396139619444
        },
        {
            "Step": 30,
            "Gini": 0.22157427757854986
        },
        {
            "Step": 31,
            "Gini": 0.22756715922571402
        },
        {
            "Step": 32,
            "Gini": 0.23207227129833474
        },
        {
            "Step": 33,
            "Gini": 0.2323960550004167
        },
        {
            "Step": 34,
            "Gini": 0.23720951712580307
        },
        {
            "Step": 35,
            "Gini": 0.23789347573601005
        },
        {
            "Step": 36,
            "Gini": 0.24244516770226765
        },
        {
            "Step": 37,
            "Gini": 0.24337131649416244
        },
        {
            "Step": 38,
            "Gini": 0.24277506160297957
        },
        {
            "Step": 39,
            "Gini": 0.2482370228271391
        },
        {
            "Step": 40,
            "Gini": 0.25222866762384566
        },
        {
            "Step": 41,
            "Gini": 0.25270124318825626
        },
        {
            "Step": 42,
            "Gini": 0.25054448968593346
        },
        {
            "Step": 43,
            "Gini": 0.2509529750803603
        },
        {
            "Step": 44,
            "Gini": 0.25487200043247715
        },
        {
            "Step": 45,
            "Gini": 0.25952492617862766
        },
        {
            "Step": 46,
            "Gini": 0.2579246994158819
        },
        {
            "Step": 47,
            "Gini": 0.2555549410110869
        },
        {
            "Step": 48,
            "Gini": 0.2592243320105416
        },
        {
            "Step": 49,
            "Gini": 0.2625745593156834
        },
        {
            "Step": 50,
            "Gini": 0.26134518494425607
        },
        {
            "Step": 51,
            "Gini": 0.2608690882039628
        },
        {
            "Step": 52,
            "Gini": 0.2600743347802301
        },
        {
            "Step": 53,
            "Gini": 0.26379355843459895
        },
        {
            "Step": 54,
            "Gini": 0.27178159941618407
        },
        {
            "Step": 55,
            "Gini": 0.2799146109944999
        },
        {
            "Step": 56,
            "Gini": 0.2814318121943993
        },
        {
            "Step": 57,
            "Gini": 0.2860672670378057
        },
        {
            "Step": 58,
            "Gini": 0.29127891522368676
        },
        {
            "Step": 59,
            "Gini": 0.29295426701609695
        },
        {
            "Step": 60,
            "Gini": 0.2918753213452179
        },
        {
            "Step": 61,
            "Gini": 0.2916637074435895
        },
        {
            "Step": 62,
            "Gini": 0.29207659588712054
        },
        {
            "Step": 63,
            "Gini": 0.29220821355407134
        },
        {
            "Step": 64,
            "Gini": 0.29584518561608486
        },
        {
            "Step": 65,
            "Gini": 0.3027928192006084
        },
        {
            "Step": 66,
            "Gini": 0.301161390704592
        },
        {
            "Step": 67,
            "Gini": 0.3017792511375028
        },
        {
            "Step": 68,
            "Gini": 0.3046679613724512
        },
        {
            "Step": 69,
            "Gini": 0.31112187514780176
        },
        {
            "Step": 70,
            "Gini": 0.31572255679308947
        },
        {
            "Step": 71,
            "Gini": 0.3245228590212299
        },
        {
            "Step": 72,
            "Gini": 0.3337011621661099
        },
        {
            "Step": 73,
            "Gini": 0.3407349330377727
        },
        {
            "Step": 74,
            "Gini": 0.34465481243654983
        },
        {
            "Step": 75,
            "Gini": 0.35089442410285154
        },
        {
            "Step": 76,
            "Gini": 0.3592441564555313
        },
        {
            "Step": 77,
            "Gini": 0.3687437640379061
        },
        {
            "Step": 78,
            "Gini": 0.37512809951703874
        },
        {
            "Step": 79,
            "Gini": 0.37829153780093216
        },
        {
            "Step": 80,
            "Gini": 0.37846026510360864
        }
    ]
]